miniws4py/__init__.py
miniws4py/compat.py
miniws4py/exc.py
miniws4py/framing.py
miniws4py/messaging.py
miniws4py/streaming.py
miniws4py/utf8validator.py
miniws4py/websocket.py
miniws4py/client/__init__.py
satori/__init__.py
satori/rtm/__init__.py
satori/rtm/auth.py
satori/rtm/client.py
satori/rtm/connection.py
satori/rtm/exceptions.py
satori/rtm/internal_client.py
satori/rtm/internal_client_action.py
satori/rtm/internal_connection_miniws4py.py
satori/rtm/internal_queue.py
satori/rtm/internal_state_machine_wrapper.py
satori/rtm/internal_subscription.py
satori/rtm/logger.py
satori/rtm/generated/__init__.py
satori/rtm/generated/client_sm.py
satori/rtm/generated/statemap.py
satori/rtm/generated/subscription_sm.py
satori_sdk_python-1.0.3.dist-info/DESCRIPTION.rst
satori_sdk_python-1.0.3.dist-info/METADATA
satori_sdk_python-1.0.3.dist-info/RECORD
satori_sdk_python-1.0.3.dist-info/WHEEL
satori_sdk_python-1.0.3.dist-info/metadata.json
satori_sdk_python-1.0.3.dist-info/top_level.txt
test/__init__.py
test/auth.py
test/badssl.py
test/changing_state_in_state_callback.py
test/channel_error.py
test/channel_search.py
test/chat_example.py
test/compat_event.py
test/connection.py
test/connection_error.py
test/delayed_publish.py
test/dummy_auth.py
test/fast_forward.py
test/filter.py
test/getattr.py
test/internal_error.py
test/kv.py
test/loggers.py
test/message_types.py
test/reconnect.py
test/resubscribe.py
test/role_auth.py
test/run_all_tests.py
test/state_callbacks.py
test/state_machines_do_not_crash.py
test/subscribe_before_start.py
test/subscribe_error.py
test/two_clients.py
test/two_identical_subscribers.py
test/unexpected.py
test/unsubscribe.py
test/unsubscribe_error.py
test/utils.py
